mvneureval/__init__.py
mvneureval/best_nclust_cv_multiview.py
mvneureval/internal_baselines_multiview.py
mvneureval/param_selection_multiview.py
mvneureval/relative_validation_multiview.py
mvneureval/utils.py
mvneureval/visualization.py
mvneureval-1.2.2.dist-info/LICENSE
mvneureval-1.2.2.dist-info/METADATA
mvneureval-1.2.2.dist-info/WHEEL
mvneureval-1.2.2.dist-info/top_level.txt
mvneureval-1.2.2.dist-info/RECORD
