Metadata-Version: 2.1
Name: mvneureval
Version: 1.2.2
Summary: Multiview stability-based relative clustering validation algorithm for multimodal data
Home-page: https://github.com/fede-colombo/Multiview_NeuReval
Author: Federica Colombo
Author-email: fcolombo.italia@gmail.com
License: UNKNOWN
Download-URL: https://github.com/fede-colombo/Multiview_NeuReval/releases/tag/v1.2.2
Platform: UNKNOWN
Classifier: Programming Language :: Python :: 3
Classifier: License :: OSI Approved :: MIT License
Classifier: Operating System :: OS Independent
Requires-Python: >=3.6
License-File: LICENSE
Requires-Dist: numpy
Requires-Dist: scipy
Requires-Dist: scikit-learn
Requires-Dist: umap-learn
Requires-Dist: matplotlib
Requires-Dist: mvlearn
